README.md
binary_wrapper.py
test_binary_wrapper.py
binary_wrapper.egg-info/PKG-INFO
binary_wrapper.egg-info/SOURCES.txt
binary_wrapper.egg-info/dependency_links.txt
binary_wrapper.egg-info/not-zip-safe
binary_wrapper.egg-info/top_level.txt
binary_wrapper-0.2.dist-info/LICENSE
binary_wrapper-0.2.dist-info/METADATA
binary_wrapper-0.2.dist-info/WHEEL
binary_wrapper-0.2.dist-info/top_level.txt
binary_wrapper-0.2.dist-info/RECORD
