Metadata-Version: 2.1
Name: binary-wrapper
Version: 0.2
Summary: A generic binary wrapper
Home-page: https://github.com/rmonico/binary_wrapper
Author: Rafael Monico
Author-email: rmonico1@gmail.com
License: GPL3
Platform: UNKNOWN
